{
  "dbnya": [
    {
      "username": "Nted",
      "password": "Nted",
      "nomor": "6289510019072"
    },
    {
      "username": "rafi",
      "password": "raf",
      "nomor": "6282286323525"
    },
    {
      "username": "zmn",
      "password": "zmn",
      "nomor": "62895345611234"
    },
    {
      "username": "ranz",
      "password": "ranz",
      "nomor": "6283861922859"
    },
    {
      "username": "kaysel",
      "password": "miayam",
      "nomor": "6281264272378"
    }
  ]
}